province_district_nepal/__init__.py
province_district_nepal/api.py
province_district_nepal-0.1.1.dist-info/licenses/LICENSE
province_district_nepal-0.1.1.dist-info/METADATA
province_district_nepal-0.1.1.dist-info/WHEEL
province_district_nepal-0.1.1.dist-info/top_level.txt
province_district_nepal-0.1.1.dist-info/RECORD
