Metadata-Version: 2.4
Name: province-district-nepal
Version: 0.1.1
Summary: A Python package to fetch districts by province in Nepal
Home-page: https://github.com/suman-bhatta/Nepal-Province-Districts-Package
Author: Suman Bhatta
Author-email: Suman Bhatta <work.suman.dev@gmail.com>
License: MIT
Classifier: Programming Language :: Python :: 3
Classifier: License :: OSI Approved :: MIT License
Classifier: Operating System :: OS Independent
Requires-Python: >=3.6
License-File: LICENSE
Dynamic: author
Dynamic: home-page
Dynamic: license-file
Dynamic: requires-python
